data/rgov.db
rgov/__init__.py
rgov/application.py
rgov/campground.py
rgov/commands/__init__.py
rgov/commands/check.py
rgov/commands/check_daemon.py
rgov/commands/initialize.py
rgov/commands/run.py
rgov/commands/search.py
rgov/dates.py
rgov/locations.py
rgov/pushsafer.py
rgov/search.py
rgov/utils.py
rgov-0.6.9.3.dist-info/LICENSE.md
rgov-0.6.9.3.dist-info/METADATA
rgov-0.6.9.3.dist-info/WHEEL
rgov-0.6.9.3.dist-info/entry_points.txt
rgov-0.6.9.3.dist-info/RECORD
