Metadata-Version: 2.1
Name: rgov
Version: 0.6.9.3
Summary: Check if campgrounds have availability on Recreation.gov
License: GPL-3.0-only
Author: Jordan Sweet
Author-email: hello@jordandsweet.com
Requires-Python: >=3.6,<4.0
Classifier: License :: OSI Approved :: GNU General Public License v3 (GPLv3)
Classifier: Programming Language :: Python :: 3
Classifier: Programming Language :: Python :: 3.6
Classifier: Programming Language :: Python :: 3.7
Classifier: Programming Language :: Python :: 3.8
Classifier: Programming Language :: Python :: 3.9
Classifier: Programming Language :: Python :: 3.10
Classifier: Programming Language :: Python :: 3.11
Requires-Dist: cleo (>=0.8.1,<0.9.0)
Requires-Dist: fake-useragent (>=1.1.1,<2.0.0)
Requires-Dist: python-daemon (>=2.3.0,<3.0.0)
